{
	"id": "b54a8baf-5f56-4c98-a555-cf775c8782dd",
	"name": "koperasi-polres",
	"values": [
		{
			"key": "BASE_URL",
			"value": "https://polres-be-fix.vercel.app",
			"type": "default",
			"enabled": true
		},
		{
			"key": "MEMBER_ID",
			"value": "cmccp5kjq0000u0o4vlt1xt8z",
			"type": "default",
			"enabled": true
		},
		{
			"key": "PIUTANG_ID",
			"value": "cmccwmjmz0009u0mw2xvpkje8",
			"type": "default",
			"enabled": true
		},
		{
			"key": "PRODUCT_ID",
			"value": "cmctz1jy00001u07ky74jhcp1",
			"type": "default",
			"enabled": true
		}
	],
	"_postman_variable_scope": "environment",
	"_postman_exported_at": "2025-07-17T14:04:36.397Z",
	"_postman_exported_using": "Postman/11.54.3"
}